{
   "description": "A fast-feudal and fast paced build order for French players with good micro and macro. \n\nPlay 1tc aggro with knights and 9 to 11 archers (to one-shot spearmen) and ram opponent if 2tc, hit them with age-up and upgrades if opponent plays FC.",
   "civilization": "French",
   "name": "French 3:38 Feudal All-in/Castle Timing",
   "author": "Valdemar1902",
   "source": "https://aoe4guides.com/builds/nU6qkr2Nm5AVL0yIZUsH",
   "build_order": [
      {
         "age": 1,
         "population_count": -1,
         "time": "0:00",
         "villager_count": 6,
         "resources": {
            "food": 6,
            "wood": 0,
            "gold": 0,
            "stone": 0,
            "builder": -1
         },
         "notes": [
            "All @unit_worker/villager.png@ to @resource/sheep.png@ (pull @resource/sheep.png@close to TC & try to get 1 @resource/sheep.png@ back home to have 4 in total)"
         ]
      },
      {
         "age": 1,
         "population_count": -1,
         "time": "0:18",
         "villager_count": 7,
         "resources": {
            "food": 7,
            "wood": 0,
            "gold": 0,
            "stone": 0,
            "builder": -1
         },
         "notes": [
            "First @unit_worker/villager.png@ to build a @building_economy/house.png@ and then to @resource/sheep.png@"
         ]
      },
      {
         "age": 1,
         "population_count": -1,
         "time": "00:36",
         "villager_count": 10,
         "resources": {
            "food": 7,
            "wood": 0,
            "gold": 3,
            "stone": 0,
            "builder": -1
         },
         "notes": [
            "3@unit_worker/villager.png@ to build @building_economy/mining-camp.png@@resource/resource_gold.png@"
         ]
      },
      {
         "age": 1,
         "population_count": -1,
         "time": "1:32",
         "villager_count": -1,
         "resources": {
            "food": 0,
            "wood": 0,
            "gold": 0,
            "stone": 0,
            "builder": -1
         },
         "notes": [
            "Rally @resource/sheep.png@ until @age/age_2.png@"
         ]
      },
      {
         "age": 1,
         "population_count": -1,
         "time": "2:15",
         "villager_count": -1,
         "resources": {
            "food": 0,
            "wood": 0,
            "gold": 0,
            "stone": 0,
            "builder": -1
         },
         "notes": [
            "Drop off all @resource/resource_food.png@and take 5 @unit_worker/villager.png@to build @landmark_french/school-of-cavalry.png@"
         ]
      },
      {
         "age": 1,
         "population_count": -1,
         "time": "2:20",
         "villager_count": -1,
         "resources": {
            "food": 0,
            "wood": 0,
            "gold": 0,
            "stone": 0,
            "builder": -1
         },
         "notes": [
            "Shift click the 5 @unit_worker/villager.png@ onto @resource/resource_wood.png@ where they will build @building_economy/house.png@@building_economy/lumber-camp.png@"
         ]
      },
      {
         "age": 1,
         "population_count": -1,
         "villager_count": -1,
         "resources": {
            "food": 0,
            "wood": 0,
            "gold": 0,
            "stone": 0,
            "builder": -1
         },
         "notes": [
            "Keep rallying @resource/resource_food.png@until 11@resource/sheep.png@"
         ]
      },
      {
         "age": 2,
         "population_count": -1,
         "time": "3:40",
         "villager_count": 18,
         "resources": {
            "food": 10,
            "wood": 5,
            "gold": 3,
            "stone": 0,
            "builder": -1
         },
         "notes": [
            "Queue @unit_french/royal-knight-2.png@ non-stop and build an @building_military/archery-range.png@ when 150 @resource/resource_wood.png@"
         ]
      },
      {
         "age": 2,
         "population_count": -1,
         "time": "4:05",
         "villager_count": 19,
         "resources": {
            "food": 11,
            "wood": 5,
            "gold": 3,
            "stone": 0,
            "builder": -1
         },
         "notes": [
            "@resource/rally.png@3 new @unit_worker/villager.png@ to @resource/resource_gold.png@ then @resource/rally.png@ to @resource/resource_food.png@after"
         ]
      },
      {
         "age": 2,
         "population_count": -1,
         "time": "8:00",
         "villager_count": -1,
         "resources": {
            "food": 0,
            "wood": 0,
            "gold": 0,
            "stone": 0,
            "builder": -1
         },
         "notes": [
            "Add @building_technology/blacksmith.png@ for +1 @technology_military/iron-undermesh.png@ to dive villagers. Add @technology_military/siege-engineering.png@ to take out 2nd TC with 2 @unit_siege/battering-ram.png@ (usually enough)"
         ]
      },
      {
         "age": 2,
         "population_count": -1,
         "villager_count": -1,
         "resources": {
            "food": 0,
            "wood": 0,
            "gold": 0,
            "stone": 0,
            "builder": -1
         },
         "notes": [
            ""
         ]
      },
      {
         "age": 2,
         "population_count": -1,
         "villager_count": -1,
         "resources": {
            "food": 0,
            "wood": 0,
            "gold": 0,
            "stone": 0,
            "builder": -1
         },
         "notes": [
            "Go castle age if opponent is going feudal aggro and you take a good fight or double down and all-in.",
            "Go rams if your opponent goes 2nd @building_economy/town-center.png@",
            "Go Units into Castle timing if opponent goes fast @age/age_3.png@",
            "",
            ""
         ]
      },
      {
         "age": 2,
         "population_count": -1,
         "villager_count": -1,
         "resources": {
            "food": 0,
            "wood": 0,
            "gold": 0,
            "stone": 0,
            "builder": -1
         },
         "notes": [
            "This strat works against most civs but vs @civilization_flag/rus.png@And @civilization_flag/chi.png@it is a lot more difficult and 2tc is more ideal."
         ]
      }
   ],
   "video": "https://www.youtube.com/embed/rJWuW9cGuKc",
   "season": "Season 6",
   "map": "Open",
   "strategy": "Rush"
}